Nexus/__init__.py
Nexus/ai.py
Nexus/bool.py
Nexus/boolo.py
Nexus/files.py
Nexus/math.py
Nexus/module.py
Nexus/websear.py
Nexus/pr/__init__.py
Nexus/pr/bool.py
Nexus/pr/boolo.py
Nexus/pr/diff.py
testfoRnExuDSA-1.0.0.dist-info/METADATA
testfoRnExuDSA-1.0.0.dist-info/WHEEL
testfoRnExuDSA-1.0.0.dist-info/top_level.txt
testfoRnExuDSA-1.0.0.dist-info/RECORD
